MemBoost/__init__.py
memboost-0.0.1.dist-info/METADATA
memboost-0.0.1.dist-info/WHEEL
memboost-0.0.1.dist-info/top_level.txt
memboost-0.0.1.dist-info/RECORD
