Metadata-Version: 2.4
Name: memboost
Version: 0.0.1
Summary: Memory Boost.
Requires-Python: >=3.8
